CHANGES.md
LICENSE.txt
MANIFEST.in
README.md
RELEASE_NOTES.txt
requirements.txt
setup.py
test/test_dmrs_query.py
test/test_search.py
test/test_setup.py
test/test_util.py
visko/__init__.py
visko/__main__.py
visko/__version__.py
visko/config.py
visko/tools.py
visko/util.py
visko.egg-info/PKG-INFO
visko.egg-info/SOURCES.txt
visko.egg-info/dependency_links.txt
visko.egg-info/requires.txt
visko.egg-info/top_level.txt
visko/kopasu/__init__.py
visko/kopasu/bibman.py
visko/kopasu/dao.py
visko/kopasu/dmrs_search.py
visko/kopasu/xmldao.py
visko/merchant/__init__.py
visko/merchant/morph.py
visko/merchant/redwood.py
visko/web/__init__.py
visko/web/admin.py
visko/web/apps.py
visko/web/models.py
visko/web/tests.py
visko/web/urls.py
visko/web/views.py
visko/web/templates/visko2/base.html
visko/web/templates/visko2/delviz.html
visko/web/templates/visko2/yawol.html
visko/web/templates/visko2/corpus/collection.html
visko/web/templates/visko2/corpus/corpus.html
visko/web/templates/visko2/corpus/document.html
visko/web/templates/visko2/corpus/index.html
visko/web/templates/visko2/corpus/parse.html
visko/web/templates/visko2/corpus/search.html
visko/web/templates/visko2/corpus/sentence.html
visko/web/templates/visko2/delviz/index.html
visko/web/templates/visko2/dev/index.html
visko/web/templates/visko2/dev/isf.html
visko/web/templates/visko2/dev/visko2.html
visko/web/templates/visko2/home/index.html
visko/web/templates/visko2/isf/editor.html
visko/web/templates/visko2/isf/index.html
visko/web/templates/visko2/yawol/index.html
visko/web/templatetags/__init__.py
visko/web/templatetags/visko2_tags.py