Metadata-Version: 2.1
Name: visko
Version: 0.2.3b4
Summary: Web-based software suite for Computational Linguistic Analysis based on construction grammars and ontologies (HPSG, SBCG, xMRS, Wordnet, texttaglib)
Home-page: https://github.com/letuananh/visualkopasu/
Author: Le Tuan Anh
Author-email: tuananh.ke@gmail.com
License: GNU General Public License v3 (GPLv3)
Project-URL: Bug Tracker, https://github.com/letuananh/visualkopasu/issues
Project-URL: Source Code, https://github.com/letuananh/visualkopasu/
Keywords: natural-language-understanding,semantics,deep-parser,ontology,wordnet,hpsg,mrs,dmrs,sbcg,corpus,linguistics,nlp,natural-language-processing
Platform: any
Classifier: Programming Language :: Python
Classifier: Development Status :: 4 - Beta
Classifier: License :: OSI Approved :: GNU General Public License v3 (GPLv3)
Classifier: Environment :: Plugins
Classifier: Environment :: Web Environment
Classifier: Intended Audience :: Education
Classifier: Intended Audience :: Science/Research
Classifier: Intended Audience :: Information Technology
Classifier: Intended Audience :: Developers
Classifier: Operating System :: OS Independent
Classifier: Topic :: Text Processing
Classifier: Topic :: Text Processing :: Linguistic
Classifier: Topic :: Software Development :: Libraries :: Python Modules
Requires-Python: >=3.6
